mango.py
mango_async.py
req.py
mango_framework-1.5.2.dist-info/METADATA
mango_framework-1.5.2.dist-info/WHEEL
mango_framework-1.5.2.dist-info/top_level.txt
mango_framework-1.5.2.dist-info/RECORD
