Metadata-Version: 2.1
Name: mango-framework
Version: 1.5.2
Summary: A lightweight and highly customizable Python framework for building web applications
Home-page: https://github.com/momo-AUX1/mango
Author: Mohammed
Author-email: fdlnaal@gmail.com
Classifier: License :: OSI Approved :: MIT License
Classifier: Programming Language :: Python :: 3
Classifier: Programming Language :: Python :: 3.6
Classifier: Programming Language :: Python :: 3.7
Classifier: Programming Language :: Python :: 3.8
Classifier: Programming Language :: Python :: 3.9
Classifier: Operating System :: OS Independent
Requires-Python: >=3.6
